{
  "version": "2.3.5",
  "flags": {},
  "shapes": [
    {
      "label": "gap",
      "points": [
        [
          127.39229024943312,
          34.399092970521544
        ],
        [
          168.20861678004536,
          34.399092970521544
        ],
        [
          168.20861678004536,
          76.34920634920636
        ],
        [
          127.39229024943312,
          76.34920634920636
        ]
      ],
      "group_id": null,
      "description": "",
      "difficult": false,
      "shape_type": "rectangle",
      "flags": {},
      "attributes": {}
    }
  ],
  "imagePath": "capture (97).png",
  "imageData": null,
  "imageHeight": 140,
  "imageWidth": 360
}